__init__.py
cycxchg.py
sparseb.py
cycxchg-0.0.2.dist-info/licenses/LICENSE
cycxchg-0.0.2.dist-info/METADATA
cycxchg-0.0.2.dist-info/WHEEL
cycxchg-0.0.2.dist-info/top_level.txt
cycxchg-0.0.2.dist-info/RECORD
