Metadata-Version: 2.4
Name: cycxchg
Version: 0.0.2
Summary: Cycle exchange: sampling the minimum cycle bases of a graph
Author-email: Perrin Ruth <pruth@umd.edu>
License-Expression: MIT
Project-URL: Homepage, https://github.com/perrineruth/Sampling_Minimum_Cycle_Bases
Project-URL: Issues, https://github.com/perrineruth/Sampling_Minimum_Cycle_Bases/issues
Classifier: Programming Language :: Python :: 3
Classifier: Operating System :: OS Independent
Requires-Python: >=3.9
License-File: LICENSE
Requires-Dist: networkx
Requires-Dist: numpy
Requires-Dist: matplotlib
Dynamic: license-file
